{
    "swagger": "2.0",
    "info": {
        "title": "Bookshop API",
        "contact": {},
        "version": "1.0"
    },
    "host": "localhost:8080",
    "basePath": "/",
    "paths": {
        "/books": {
            "get": {
                "description": "Get all books",
                "produces": [
                    "application/json"
                ],
                "tags": [
                    "books"
                ],
                "summary": "Get Books",
                "responses": {
                    "200": {
                        "description": "OK",
                        "schema": {
                            "type": "array",
                            "items": {
                                "$ref": "#/definitions/model.Book"
                            }
                        }
                    }
                }
            },
            "post": {
                "description": "Create new book",
                "consumes": [
                    "application/json"
                ],
                "produces": [
                    "application/json"
                ],
                "tags": [
                    "books"
                ],
                "summary": "Create book",
                "parameters": [
                    {
                        "description": "Book data",
                        "name": "book",
                        "in": "body",
                        "required": true,
                        "schema": {
                            "$ref": "#/definitions/model.CreateBookModel"
                        }
                    }
                ],
                "responses": {
                    "201": {
                        "description": "Created",
                        "schema": {
                            "$ref": "#/definitions/model.Book"
                        }
                    },
                    "400": {
                        "description": "Bad Request",
                        "schema": {
                            "type": "object",
                            "additionalProperties": {
                                "type": "string"
                            }
                        }
                    },
                    "500": {
                        "description": "Internal Server Error",
                        "schema": {
                            "type": "object",
                            "additionalProperties": {
                                "type": "string"
                            }
                        }
                    }
                }
            }
        },
        "/books/{id}": {
            "get": {
                "description": "Get single user",
                "produces": [
                    "application/json"
                ],
                "tags": [
                    "books"
                ],
                "summary": "Get book by ID",
                "parameters": [
                    {
                        "type": "integer",
                        "description": "Book ID",
                        "name": "id",
                        "in": "path",
                        "required": true
                    }
                ],
                "responses": {
                    "200": {
                        "description": "OK",
                        "schema": {
                            "$ref": "#/definitions/model.Book"
                        }
                    },
                    "400": {
                        "description": "Bad Request",
                        "schema": {
                            "type": "object",
                            "additionalProperties": {
                                "type": "string"
                            }
                        }
                    },
                    "500": {
                        "description": "Internal Server Error",
                        "schema": {
                            "type": "object",
                            "additionalProperties": {
                                "type": "string"
                            }
                        }
                    }
                }
            },
            "put": {
                "description": "Update book by ID",
                "consumes": [
                    "application/json"
                ],
                "produces": [
                    "application/json"
                ],
                "tags": [
                    "books"
                ],
                "summary": "Update book",
                "parameters": [
                    {
                        "type": "integer",
                        "description": "Book ID",
                        "name": "id",
                        "in": "path",
                        "required": true
                    },
                    {
                        "description": "Update book data",
                        "name": "user",
                        "in": "body",
                        "required": true,
                        "schema": {
                            "$ref": "#/definitions/model.UpdateBookModel"
                        }
                    }
                ],
                "responses": {
                    "200": {
                        "description": "OK",
                        "schema": {
                            "type": "object",
                            "additionalProperties": {
                                "type": "string"
                            }
                        }
                    },
                    "400": {
                        "description": "Bad Request",
                        "schema": {
                            "type": "object",
                            "additionalProperties": {
                                "type": "string"
                            }
                        }
                    },
                    "500": {
                        "description": "Internal Server Error",
                        "schema": {
                            "type": "object",
                            "additionalProperties": {
                                "type": "string"
                            }
                        }
                    }
                }
            },
            "delete": {
                "description": "Delete book by ID",
                "consumes": [
                    "application/json"
                ],
                "produces": [
                    "application/json"
                ],
                "tags": [
                    "books"
                ],
                "summary": "Delete book",
                "parameters": [
                    {
                        "type": "integer",
                        "description": "Book ID",
                        "name": "id",
                        "in": "path",
                        "required": true
                    }
                ],
                "responses": {
                    "200": {
                        "description": "OK",
                        "schema": {
                            "type": "object",
                            "additionalProperties": {
                                "type": "string"
                            }
                        }
                    },
                    "400": {
                        "description": "Bad Request",
                        "schema": {
                            "type": "object",
                            "additionalProperties": {
                                "type": "string"
                            }
                        }
                    },
                    "500": {
                        "description": "Internal Server Error",
                        "schema": {
                            "type": "object",
                            "additionalProperties": {
                                "type": "string"
                            }
                        }
                    }
                }
            }
        },
        "/createUser": {
            "post": {
                "description": "Create new user",
                "consumes": [
                    "application/json"
                ],
                "produces": [
                    "application/json"
                ],
                "tags": [
                    "users"
                ],
                "summary": "Create user",
                "parameters": [
                    {
                        "description": "User data",
                        "name": "user",
                        "in": "body",
                        "required": true,
                        "schema": {
                            "$ref": "#/definitions/model.CreateUserRequest"
                        }
                    }
                ],
                "responses": {
                    "201": {
                        "description": "Created",
                        "schema": {
                            "$ref": "#/definitions/model.User"
                        }
                    },
                    "400": {
                        "description": "Bad Request",
                        "schema": {
                            "type": "object",
                            "additionalProperties": {
                                "type": "string"
                            }
                        }
                    }
                }
            }
        },
        "/login": {
            "post": {
                "description": "Login user",
                "consumes": [
                    "application/json"
                ],
                "produces": [
                    "application/json"
                ],
                "tags": [
                    "users"
                ],
                "summary": "Login user",
                "parameters": [
                    {
                        "description": "Login data",
                        "name": "user",
                        "in": "body",
                        "required": true,
                        "schema": {
                            "$ref": "#/definitions/model.LoginUserModel"
                        }
                    }
                ],
                "responses": {
                    "200": {
                        "description": "OK",
                        "schema": {
                            "type": "object",
                            "additionalProperties": {
                                "type": "string"
                            }
                        }
                    },
                    "400": {
                        "description": "Bad Request",
                        "schema": {
                            "type": "object",
                            "additionalProperties": {
                                "type": "string"
                            }
                        }
                    }
                }
            }
        },
        "/users": {
            "get": {
                "security": [
                    {
                        "BearerAuth": []
                    }
                ],
                "description": "Get all users",
                "produces": [
                    "application/json"
                ],
                "tags": [
                    "users"
                ],
                "summary": "Get users",
                "responses": {
                    "200": {
                        "description": "OK",
                        "schema": {
                            "type": "array",
                            "items": {
                                "$ref": "#/definitions/model.User"
                            }
                        }
                    }
                }
            }
        },
        "/users/{id}": {
            "get": {
                "description": "Get single user",
                "produces": [
                    "application/json"
                ],
                "tags": [
                    "users"
                ],
                "summary": "Get user by ID",
                "parameters": [
                    {
                        "type": "integer",
                        "description": "User ID",
                        "name": "id",
                        "in": "path",
                        "required": true
                    }
                ],
                "responses": {
                    "200": {
                        "description": "OK",
                        "schema": {
                            "$ref": "#/definitions/model.User"
                        }
                    },
                    "400": {
                        "description": "Bad Request",
                        "schema": {
                            "type": "object",
                            "additionalProperties": {
                                "type": "string"
                            }
                        }
                    },
                    "500": {
                        "description": "Internal Server Error",
                        "schema": {
                            "type": "object",
                            "additionalProperties": {
                                "type": "string"
                            }
                        }
                    }
                }
            },
            "put": {
                "description": "Update user by ID",
                "consumes": [
                    "application/json"
                ],
                "produces": [
                    "application/json"
                ],
                "tags": [
                    "users"
                ],
                "summary": "Update user",
                "parameters": [
                    {
                        "type": "integer",
                        "description": "User ID",
                        "name": "id",
                        "in": "path",
                        "required": true
                    },
                    {
                        "description": "Update user data",
                        "name": "user",
                        "in": "body",
                        "required": true,
                        "schema": {
                            "$ref": "#/definitions/model.UpdateUserModel"
                        }
                    }
                ],
                "responses": {
                    "200": {
                        "description": "OK",
                        "schema": {
                            "type": "object",
                            "additionalProperties": {
                                "type": "string"
                            }
                        }
                    },
                    "400": {
                        "description": "Bad Request",
                        "schema": {
                            "type": "object",
                            "additionalProperties": {
                                "type": "string"
                            }
                        }
                    },
                    "500": {
                        "description": "Internal Server Error",
                        "schema": {
                            "type": "object",
                            "additionalProperties": {
                                "type": "string"
                            }
                        }
                    }
                }
            },
            "delete": {
                "description": "Delete user by ID",
                "consumes": [
                    "application/json"
                ],
                "produces": [
                    "application/json"
                ],
                "tags": [
                    "users"
                ],
                "summary": "Delete user",
                "parameters": [
                    {
                        "type": "integer",
                        "description": "User ID",
                        "name": "id",
                        "in": "path",
                        "required": true
                    }
                ],
                "responses": {
                    "200": {
                        "description": "OK",
                        "schema": {
                            "type": "object",
                            "additionalProperties": {
                                "type": "string"
                            }
                        }
                    },
                    "400": {
                        "description": "Bad Request",
                        "schema": {
                            "type": "object",
                            "additionalProperties": {
                                "type": "string"
                            }
                        }
                    },
                    "500": {
                        "description": "Internal Server Error",
                        "schema": {
                            "type": "object",
                            "additionalProperties": {
                                "type": "string"
                            }
                        }
                    }
                }
            }
        }
    },
    "definitions": {
        "model.Book": {
            "type": "object",
            "properties": {
                "author": {
                    "type": "string"
                },
                "id": {
                    "type": "integer"
                },
                "quantity": {
                    "type": "integer"
                },
                "title": {
                    "type": "string"
                }
            }
        },
        "model.CreateBookModel": {
            "type": "object",
            "properties": {
                "author": {
                    "type": "string"
                },
                "quantity": {
                    "type": "integer"
                },
                "title": {
                    "type": "string"
                }
            }
        },
        "model.CreateUserRequest": {
            "type": "object",
            "properties": {
                "gmail": {
                    "type": "string"
                },
                "name": {
                    "type": "string"
                },
                "password": {
                    "type": "string"
                },
                "username": {
                    "type": "string"
                }
            }
        },
        "model.LoginUserModel": {
            "type": "object",
            "properties": {
                "password": {
                    "type": "string"
                },
                "username": {
                    "type": "string"
                }
            }
        },
        "model.UpdateBookModel": {
            "type": "object",
            "properties": {
                "author": {
                    "type": "string"
                },
                "quantity": {
                    "type": "integer"
                },
                "title": {
                    "type": "string"
                }
            }
        },
        "model.UpdateUserModel": {
            "type": "object",
            "properties": {
                "gmail": {
                    "type": "string"
                },
                "name": {
                    "type": "string"
                },
                "password": {
                    "type": "string"
                },
                "username": {
                    "type": "string"
                }
            }
        },
        "model.User": {
            "type": "object",
            "properties": {
                "gmail": {
                    "type": "string"
                },
                "id": {
                    "type": "integer",
                    "format": "int64"
                },
                "name": {
                    "type": "string"
                },
                "password": {
                    "type": "string"
                },
                "userName": {
                    "type": "string"
                }
            }
        }
    },
    "securityDefinitions": {
        "BearerAuth": {
            "type": "apiKey",
            "name": "Authorization",
            "in": "header"
        }
    }
}